Workbook

Sheet Summary
A1: Commercial construct — two-year delivery envelope + one-year AMC | C1: USD
A2: 1 · Platform licence (the built platform, both portals) | B2: Derived: target minus all other components — see implied effort below | C2: =C13-SUM(C3:C10) -> 1676563
A3: 2 · Delta development (70:30 offshore/onshore) | B3: 218 person-months per DeltaDev | C3: =DeltaDev!N11 -> 2171290
A4: 3 · Contingency on development | B4: Rate below | C4: =C3*C14 -> 217129
A5: 4 · Training delivery (non-labour) | B5: OtherCosts | C5: =OtherCosts!C2 -> 60000
A6: 5 · Travel, lodging & boarding | B6: TravelLodging | C6: =TravelLodging!E6 -> 372018
A7: 6 · Software licences & tooling | B7: OtherCosts | C7: =OtherCosts!C3 -> 160000
A8: 7 · Local compliance & certification | B8: OtherCosts | C8: =OtherCosts!C4 -> 95000
A9: 8 · Miscellaneous & mobilisation + optional cloud | B9: OtherCosts | C9: =OtherCosts!C5+OtherCosts!C6 -> 80000
A10: 9 · AMC — Year 1 | B10: AMC sheet (per-year price; client may extend at the escalation table) | C10: =AMC!F8 -> 568000
A11: TOTAL | C11: =SUM(C2:C10) -> 5400000
A13: Total Final Commercials | B13: Fixed commercial target | C13: 5400000
A14: Contingency rate | B14: editable | C14: 0.1

Sheet RateCards
A1: Role | B1: Offshore rate (USD/mo) | C1: Onshore UAE rate (USD/mo) | D1: Notes
A2: Programme Manager | B2: 9500 | C2: 21000 | D2: Client-facing governance — onshore-led
A3: Solution Architect | B3: 11000 | C3: 24000 | D3: Onshore for design and drop windows
A4: Technical Lead | B4: 8000 | C4: 17500 | D4: Workstream leads; onshore rotations
A5: Senior Engineer | B5: 6500 | C5: 14500 | D5: Platform and domain services
A6: Engineer | B6: 4800 | C6: 11000 | D6: Feature build — offshore
A7: AI/ML Engineer | B7: 8500 | C7: 19000 | D7: Agents, models, evaluation
A8: QA Engineer | B8: 4200 | C8: 9500 | D8: Automation-first; onshore for UAT
A9: DevOps Engineer | B9: 6500 | C9: 14500 | D9: Chassis, CI/CD, environments
A10: BA / Domain SME | B10: 5500 | C10: 13000 | D10: Ministry workshops, UAT — onshore-led
A11: Support Engineer (AMC L2/L3) | B11: 6500 | C11: 14500 | D11: Post-go-live support pod
A12: Service Delivery Manager (AMC) | B12: 9500 | C12: 21000 | D12: AMC governance, SLA reporting
A14: NOTE: onshore rates are labour only — lodging, boarding and travel are costed separately in this model.

Sheet DeltaDev
A1: Role (FTE per window) | B1: M0–M2 | C1: M3–M5 | D1: M6–M8 | E1: M9–M11 | F1: M12–M14 | G1: M15 | H1: Person-months | I1: Onshore share | J1: Onshore MM | K1: Offshore MM | L1: Onshore cost | M1: Offshore cost | N1: Role cost
A2: Programme Manager | B2: 1 | C2: 1 | D2: 1 | E2: 1 | F2: 1 | G2: 1 | H2: =B2*3+C2*3+D2*3+E2*3+F2*3+G2*1 -> 16 | I2: 1 | J2: =H2*I2 -> 16 | K2: =H2*(1-I2) -> 0 | L2: =J2*INDEX(RateCards!C:C,MATCH(A2,RateCards!A:A,0)) -> 336000 | M2: =K2*INDEX(RateCards!B:B,MATCH(A2,RateCards!A:A,0)) -> 0 | N2: =L2+M2 -> 336000
A3: Solution Architect | B3: 1 | C3: 1 | D3: 1 | E3: 1 | F3: 0.5 | G3: 0 | H3: =B3*3+C3*3+D3*3+E3*3+F3*3+G3*1 -> 13.5 | I3: 0.6 | J3: =H3*I3 -> 8.1 | K3: =H3*(1-I3) -> 5.4 | L3: =J3*INDEX(RateCards!C:C,MATCH(A3,RateCards!A:A,0)) -> 194400 | M3: =K3*INDEX(RateCards!B:B,MATCH(A3,RateCards!A:A,0)) -> 59400 | N3: =L3+M3 -> 253800
A4: Technical Lead | B4: 1 | C4: 2 | D4: 3 | E4: 3 | F4: 2 | G4: 1 | H4: =B4*3+C4*3+D4*3+E4*3+F4*3+G4*1 -> 34 | I4: 0.4 | J4: =H4*I4 -> 13.6 | K4: =H4*(1-I4) -> 20.4 | L4: =J4*INDEX(RateCards!C:C,MATCH(A4,RateCards!A:A,0)) -> 238000 | M4: =K4*INDEX(RateCards!B:B,MATCH(A4,RateCards!A:A,0)) -> 163200 | N4: =L4+M4 -> 401200
A5: Senior Engineer | B5: 2 | C5: 4 | D5: 5 | E5: 5 | F5: 3 | G5: 2 | H5: =B5*3+C5*3+D5*3+E5*3+F5*3+G5*1 -> 59 | I5: 0.2 | J5: =H5*I5 -> 11.8 | K5: =H5*(1-I5) -> 47.2 | L5: =J5*INDEX(RateCards!C:C,MATCH(A5,RateCards!A:A,0)) -> 171100 | M5: =K5*INDEX(RateCards!B:B,MATCH(A5,RateCards!A:A,0)) -> 306800 | N5: =L5+M5 -> 477900
A6: Engineer | B6: 1 | C6: 2 | D6: 3 | E6: 3 | F6: 2 | G6: 1 | H6: =B6*3+C6*3+D6*3+E6*3+F6*3+G6*1 -> 34 | I6: 0 | J6: =H6*I6 -> 0 | K6: =H6*(1-I6) -> 34 | L6: =J6*INDEX(RateCards!C:C,MATCH(A6,RateCards!A:A,0)) -> 0 | M6: =K6*INDEX(RateCards!B:B,MATCH(A6,RateCards!A:A,0)) -> 163200 | N6: =L6+M6 -> 163200
A7: AI/ML Engineer | B7: 1 | C7: 2 | D7: 2 | E7: 2 | F7: 1.5 | G7: 0.5 | H7: =B7*3+C7*3+D7*3+E7*3+F7*3+G7*1 -> 26 | I7: 0.25 | J7: =H7*I7 -> 6.5 | K7: =H7*(1-I7) -> 19.5 | L7: =J7*INDEX(RateCards!C:C,MATCH(A7,RateCards!A:A,0)) -> 123500 | M7: =K7*INDEX(RateCards!B:B,MATCH(A7,RateCards!A:A,0)) -> 165750 | N7: =L7+M7 -> 289250
A8: QA Engineer | B8: 0 | C8: 1 | D8: 1.5 | E8: 1.5 | F8: 1.5 | G8: 1.5 | H8: =B8*3+C8*3+D8*3+E8*3+F8*3+G8*1 -> 18 | I8: 0.1 | J8: =H8*I8 -> 1.8 | K8: =H8*(1-I8) -> 16.2 | L8: =J8*INDEX(RateCards!C:C,MATCH(A8,RateCards!A:A,0)) -> 17100 | M8: =K8*INDEX(RateCards!B:B,MATCH(A8,RateCards!A:A,0)) -> 68040 | N8: =L8+M8 -> 85140
A9: DevOps Engineer | B9: 0.5 | C9: 0.5 | D9: 1 | E9: 1 | F9: 0.5 | G9: 0.5 | H9: =B9*3+C9*3+D9*3+E9*3+F9*3+G9*1 -> 11 | I9: 0.1 | J9: =H9*I9 -> 1.1 | K9: =H9*(1-I9) -> 9.9 | L9: =J9*INDEX(RateCards!C:C,MATCH(A9,RateCards!A:A,0)) -> 15950 | M9: =K9*INDEX(RateCards!B:B,MATCH(A9,RateCards!A:A,0)) -> 64350 | N9: =L9+M9 -> 80300
A10: BA / Domain SME | B10: 0.5 | C10: 0.5 | D10: 0.5 | E10: 0.5 | F10: 0 | G10: 0.5 | H10: =B10*3+C10*3+D10*3+E10*3+F10*3+G10*1 -> 6.5 | I10: 1 | J10: =H10*I10 -> 6.5 | K10: =H10*(1-I10) -> 0 | L10: =J10*INDEX(RateCards!C:C,MATCH(A10,RateCards!A:A,0)) -> 84500 | M10: =K10*INDEX(RateCards!B:B,MATCH(A10,RateCards!A:A,0)) -> 0 | N10: =L10+M10 -> 84500
A11: Total | B11: =SUM(B2:B10) -> 8 | C11: =SUM(C2:C10) -> 14 | D11: =SUM(D2:D10) -> 18 | E11: =SUM(E2:E10) -> 18 | F11: =SUM(F2:F10) -> 12 | G11: =SUM(G2:G10) -> 8 | H11: =SUM(H2:H10) -> 218 | J11: =SUM(J2:J10) -> 65.4 | K11: =SUM(K2:K10) -> 152.6 | L11: =SUM(L2:L10) -> 1180550 | M11: =SUM(M2:M10) -> 990740 | N11: =SUM(N2:N10) -> 2171290
A12: Onshore share of MM (target 30%) | I12: =J11/H11 -> 0.3

Sheet AMC
A1: AMC support pod (per year) | B1: FTE | C1: Location | D1: Rate (USD/mo) | E1: Months | F1: Cost (USD)
A2: Support Engineer (AMC L2/L3) | B2: 3 | C2: Offshore | D2: =INDEX(RateCards!B:B,MATCH(A2,RateCards!A:A,0)) -> 6500 | E2: 12 | F2: =B2*D2*E2 -> 234000
A3: Support Engineer (AMC L2/L3) | B3: 0.5 | C3: Onshore | D3: =INDEX(RateCards!C:C,MATCH(A3,RateCards!A:A,0)) -> 14500 | E3: 12 | F3: =B3*D3*E3 -> 87000
A4: AI/ML Engineer | B4: 0.5 | C4: Offshore | D4: =INDEX(RateCards!B:B,MATCH(A4,RateCards!A:A,0)) -> 8500 | E4: 12 | F4: =B4*D4*E4 -> 51000
A5: DevOps Engineer | B5: 0.5 | C5: Offshore | D5: =INDEX(RateCards!B:B,MATCH(A5,RateCards!A:A,0)) -> 6500 | E5: 12 | F5: =B5*D5*E5 -> 39000
A6: Service Delivery Manager (AMC) | B6: 0.5 | C6: Onshore | D6: =INDEX(RateCards!C:C,MATCH(A6,RateCards!A:A,0)) -> 21000 | E6: 12 | F6: =B6*D6*E6 -> 126000
A7: Tooling, monitoring & SLA reporting stack | F7: 31000
A8: AMC Year-1 price | F8: =SUM(F2:F7) -> 568000
A10: Covers: 24/7 P1 support per RFP §6.1 SLAs · model drift monitoring (§6.6) · quarterly AI adoption reporting (D12) · patches per §6.5 clocks
A11: Extension pricing (client option): | B11: Years | C11: Escalation p.a. | D11: Price
A12: Year 2 | B12: 2 | C12: 0.03 | D12: =F8*(1+C12) -> 585040
A13: Year 3 | B13: 3 | C13: 0.03 | D13: =F8*(1+C13)^2 -> 602591.2
A14: Year 4 | B14: 4 | C14: 0.03 | D14: =F8*(1+C14)^3 -> 620668.94
A15: Year 5 | B15: 5 | C15: 0.03 | D15: =F8*(1+C15)^4 -> 639289
A17: AMC Year 1 runs twelve months from hypercare exit (end M18); instalments are billed quarterly in arrears from that date.

Sheet TravelLodging
A1: Item | B1: Qty | C1: Unit | D1: Rate (USD) | E1: Cost (USD)
A2: Return flights (rotations, mobilisation, leadership reviews) | B2: 70 | C2: trips | D2: 1200 | E2: =B2*D2 -> 84000
A3: Lodging & boarding — onshore stays | B3: =DeltaDev!J11 -> 65.4 | C3: person-months | D3: 3670 | E3: =B3*D3 -> 240018
A4: Local transport & UAE mobility | C4: lump sum | E4: 24000
A5: Visas & work permits | B5: 30 | C5: permits | D5: 800 | E5: =B5*D5 -> 24000
A6: Total travel, lodging & boarding | E6: =SUM(E2:E5) -> 372018
A8: Lodging basis: serviced apartment ~2,700 + boarding per-diem ~970 per onshore person-month. Onshore labour rates in RateCards exclude these.

Sheet OtherCosts
A1: Item | B1: Detail | C1: Cost (USD)
A2: Training delivery (non-labour) | B2: Bilingual AR/EN materials, translation, training lab environments, venues; trainer effort is inside the development estimate (D10) | C2: 60000
A3: Software licences & tooling (delivery period) | B3: APM/monitoring, code quality, test & load tooling, design/collab licences for the programme team | C3: 160000
A4: Local compliance & certification | B4: UAE-accredited VAPT (annual, §6.5), TDRA accessibility audit (§5.9), PDPL/data-residency advisory, security-standards alignment (§7.4) | C4: 95000
A5: Miscellaneous & mobilisation | B5: Insurance, communications, logistics, workspace, mobilisation/demobilisation | C5: 80000
A6: Cloud consumption (optional — default client-side) | B6: Azure subscription assumed held by the Authority; set a value here only if vendor-carried | C6: 0
A7: Total other costs | C7: =SUM(C2:C6) -> 395000

Sheet Milestones
A1: Payment schedule | D1: Delivery price (total minus AMC): | E1: =Summary!C13-Summary!C10 -> 4832000
A2: # | B2: Milestone | C2: When | D2: Share | E2: USD
A3: 1 | B3: Contract signature & mobilisation | C3: M0 | D3: 0.1 | E3: =D3*$E$1 -> 483200
A4: 2 | B4: Architecture & design baseline (D1) accepted | C4: M5 | D4: 0.1 | E4: =D4*$E$1 -> 483200
A5: 3 | B5: Drop 1 accepted — MDM, Ships, Legislation; A1/A3/A4/A6; UAE PASS | C5: M7 | D5: 0.15 | E5: =D5*$E$1 -> 724800
A6: 4 | B6: Drop 2 accepted — Seafarers, NMC live feeds, Smart Inspection + inspector app; A2/A5/A7 | C6: M11 | D6: 0.15 | E6: =D6*$E$1 -> 724800
A7: 5 | B7: Drop 3 accepted — Ports, Facilities, Revenue + gateway; dashboards; customer app; LCNC GA | C7: M14 | D7: 0.15 | E7: =D7*$E$1 -> 724800
A8: 6 | B8: Migration approved & UAT complete | C8: M15 | D8: 0.1 | E8: =D8*$E$1 -> 483200
A9: 7 | B9: Go-Live (T0) | C9: end M15 | D9: 0.15 | E9: =D9*$E$1 -> 724800
A10: 8 | B10: Hypercare exit & operational handover | C10: M18 | D10: 0.1 | E10: =D10*$E$1 -> 483200
B11: Delivery milestones total | D11: =SUM(D3:D10) -> 1 | E11: =SUM(E3:E10) -> 4832000
B13: AMC Year 1 — billed quarterly in arrears from AMC start (hypercare exit, end M18)
B14: Quarter 1 | C14: AMC month 1–3 | E14: =Summary!C10/4 -> 142000
B15: Quarter 2 | C15: AMC month 4–6 | E15: =Summary!C10/4 -> 142000
B16: Quarter 3 | C16: AMC month 7–9 | E16: =Summary!C10/4 -> 142000
B17: Quarter 4 | C17: AMC month 10–12 | E17: =Summary!C10/4 -> 142000
B18: GRAND TOTAL — delivery + AMC Year 1 | E18: =E11+SUM(E14:E17) -> 5400000
B19: Check vs target price (should be 0) | E19: =E18-Summary!C13 -> 0
